Metadata-Version: 2.4
Name: synthetic_home
Version: 5.0.2
Summary: Library for managing synthetic home device registry
Author-email: Allen Porter <allen.porter@gmail.com>
License-Expression: Apache-2.0
Project-URL: Source, https://github.com/allenporter/synthetic_home
Requires-Python: >=3.13
License-File: LICENSE
Requires-Dist: mashumaro>=3.13
Requires-Dist: aiohttp>=3.9.5
Dynamic: license-file
